routeutils/__init__.py
routeutils/routeanalyser.py
routeutils-0.1.1.dist-info/LICENSE
routeutils-0.1.1.dist-info/METADATA
routeutils-0.1.1.dist-info/WHEEL
routeutils-0.1.1.dist-info/top_level.txt
routeutils-0.1.1.dist-info/RECORD
